Metadata-Version: 2.1
Name: psfr
Version: 0.1.0
Summary: Telescope Images Point Spread Function Reconstruction
Home-page: https://github.com/sibirrer/psfr
Author: Simon Birrer
Author-email: sibirrer@gmail.com
License: BSD 3-Clause
Keywords: psfr
Platform: UNKNOWN
Classifier: Development Status :: 5 - Production/Stable
Classifier: Intended Audience :: Developers
Classifier: Natural Language :: English
Classifier: Programming Language :: Python :: 3
Classifier: Programming Language :: Python :: 3.9
Classifier: Programming Language :: Python :: 3.11
Requires-Python: >=3.6
